CMRESHandler-1.0.0b4.dist-info/DESCRIPTION.rst
CMRESHandler-1.0.0b4.dist-info/METADATA
CMRESHandler-1.0.0b4.dist-info/RECORD
CMRESHandler-1.0.0b4.dist-info/WHEEL
CMRESHandler-1.0.0b4.dist-info/metadata.json
CMRESHandler-1.0.0b4.dist-info/top_level.txt
cmreslogging/__init__.py
cmreslogging/handlers.py
cmreslogging/serializers.py
tests/__init__.py
tests/test_cmreshandler.py
tests/test_cmresserializer.py
