Metadata-Version: 2.0
Name: CMRESHandler
Version: 1.0.0b4
Summary: Elasticsearch Log handler for the logging library
Home-page: https://github.com/cmanaha/python-elasticsearch-logger
Author: Carlos Manzanedo Rueda
Author-email: c.manaha@gmail.com
License: Apache2
Keywords: logging elasticsearch handler log django instrumentation
Platform: UNKNOWN
Classifier: Development Status :: 4 - Beta
Classifier: Intended Audience :: Developers
Classifier: Topic :: System :: Logging
Classifier: Topic :: Software Development :: Libraries
Classifier: Topic :: Internet :: Log Analysis
Classifier: License :: OSI Approved :: Apache Software License
Classifier: Programming Language :: Python :: 2.7
Classifier: Programming Language :: Python :: 3.6
Requires-Dist: elasticsearch
Requires-Dist: requests
Provides-Extra: dev
Requires-Dist: check-manifest; extra == 'dev'
Requires-Dist: pylint; extra == 'dev'
Requires-Dist: six; extra == 'dev'
Provides-Extra: test
Requires-Dist: coverage; extra == 'test'
